[
  {
    "Name": "Eugene Quitzon IV",
    "Credit_Card_Number": "5562846147903574",
    "Issuer": "mastercard",
    "Expiry_Date": "11/25",
    "cvv": "775"
  },
  {
    "Name": "Heather Jakubowski",
    "Credit_Card_Number": "5131635883447116",
    "Issuer": "mastercard",
    "Expiry_Date": "03/26",
    "cvv": "879"
  },
  {
    "Name": "Carmen Runte Sr.",
    "Credit_Card_Number": "5276651937618730",
    "Issuer": "mastercard",
    "Expiry_Date": "08/26",
    "cvv": "262"
  },
  {
    "Name": "Ann Jones",
    "Credit_Card_Number": "5591105472280552",
    "Issuer": "mastercard",
    "Expiry_Date": "02/25",
    "cvv": "043"
  },
  {
    "Name": "Israel Sanford",
    "Credit_Card_Number": "5384474771563261",
    "Issuer": "mastercard",
    "Expiry_Date": "05/25",
    "cvv": "723"
  }
]